{
    "decisions": [
        [
            {
                "Alice": 18.0,
                "Bob": 20.0,
                "Cindy": 32.0,
                "Dan": 22.0,
                "Eva": 25.0
            },
            {
                "Alice": 17.0,
                "Bob": 16.0,
                "Cindy": 20.0,
                "Dan": 10.0,
                "Eva": 9.0
            },
            {
                "Alice": 7.0,
                "Bob": 6.0,
                "Cindy": 8.0,
                "Dan": 7.0,
                "Eva": 8.0
            },
            {
                "Alice": 5.0,
                "Bob": 3.0,
                "Cindy": 3.0,
                "Dan": 3.0,
                "Eva": 4.0
            }
        ],
        [
            {
                "Alice": 1.0,
                "Bob": 30.0,
                "Cindy": 18.0,
                "Dan": 28.0,
                "Eva": 18.0
            },
            {
                "Alice": 11.0,
                "Bob": 12.0,
                "Cindy": 15.0,
                "Dan": 14.0,
                "Eva": 10.0
            },
            {
                "Alice": 7.0,
                "Bob": 9.0,
                "Cindy": 7.0,
                "Dan": 4.0,
                "Eva": 6.0
            },
            {
                "Alice": 5.0,
                "Bob": 2.0,
                "Cindy": 1.0,
                "Dan": 2.0,
                "Eva": 1.0
            }
        ],
        [
            {
                "Alice": 12.0,
                "Bob": 28.0,
                "Cindy": 80.0,
                "Dan": 28.0,
                "Eva": 33.0
            },
            {
                "Alice": 22.0,
                "Bob": 16.0,
                "Cindy": 24.0,
                "Dan": 13.0,
                "Eva": 25.0
            },
            {
                "Alice": 10.0,
                "Bob": 7.0,
                "Cindy": 7.0,
                "Dan": 9.0,
                "Eva": 9.0
            },
            {
                "Alice": 4.0,
                "Bob": 5.0,
                "Cindy": 2.0,
                "Dan": 5.0,
                "Eva": 4.0
            }
        ],
        [
            {
                "Alice": 26.0,
                "Bob": 28.0,
                "Cindy": 22.0,
                "Dan": 27.0,
                "Eva": 22.0
            },
            {
                "Alice": 15.0,
                "Bob": 17.0,
                "Cindy": 19.0,
                "Dan": 20.0,
                "Eva": 14.0
            },
            {
                "Alice": 9.0,
                "Bob": 10.0,
                "Cindy": 12.0,
                "Dan": 8.0,
                "Eva": 8.0
            },
            {
                "Alice": 5.0,
                "Bob": 5.0,
                "Cindy": 4.0,
                "Dan": 5.0,
                "Eva": 4.0
            }
        ],
        [
            {
                "Alice": 22.0,
                "Bob": 70.0,
                "Cindy": 22.0,
                "Dan": 25.0,
                "Eva": 33.0
            },
            {
                "Alice": 18.0,
                "Bob": 17.0,
                "Cindy": 18.0,
                "Dan": 13.0,
                "Eva": 12.0
            },
            {
                "Alice": 10.0,
                "Bob": 7.0,
                "Cindy": 6.0,
                "Dan": 6.0,
                "Eva": 8.0
            },
            {
                "Alice": 5.0,
                "Bob": 2.9,
                "Cindy": 3.0,
                "Dan": 3.0,
                "Eva": 5.0
            }
        ],
        [
            {
                "Alice": 12.0,
                "Bob": 25.0,
                "Cindy": 35.0,
                "Dan": 22.0,
                "Eva": 33.0
            },
            {
                "Alice": 13.0,
                "Bob": 13.0,
                "Cindy": 40.0,
                "Dan": 10.0,
                "Eva": 13.0
            },
            {
                "Alice": 10.0,
                "Bob": 11.0,
                "Cindy": 7.0,
                "Dan": 10.0,
                "Eva": 9.0
            },
            {
                "Alice": 4.0,
                "Bob": 5.0,
                "Cindy": 6.0,
                "Dan": 4.0,
                "Eva": 5.0
            }
        ],
        [
            {
                "Alice": 33.0,
                "Bob": 22.0,
                "Cindy": 27.0,
                "Dan": 50.0,
                "Eva": 33.0
            },
            {
                "Alice": 18.0,
                "Bob": 19.0,
                "Cindy": 18.0,
                "Dan": 17.0,
                "Eva": 26.0
            },
            {
                "Alice": 14.0,
                "Bob": 10.0,
                "Cindy": 9.0,
                "Dan": 9.0,
                "Eva": 11.0
            },
            {
                "Alice": 4.0,
                "Bob": 6.0,
                "Cindy": 3.0,
                "Dan": 7.0,
                "Eva": 5.0
            }
        ],
        [
            {
                "Alice": 26.0,
                "Bob": 18.0,
                "Cindy": 5.0,
                "Dan": 33.0,
                "Eva": 28.0
            },
            {
                "Alice": 14.0,
                "Bob": 11.0,
                "Cindy": 15.0,
                "Dan": 14.0,
                "Eva": 12.0
            },
            {
                "Alice": 7.0,
                "Bob": 8.0,
                "Cindy": 6.0,
                "Dan": 6.0,
                "Eva": 6.0
            },
            {
                "Alice": 4.0,
                "Bob": 2.0,
                "Cindy": 3.0,
                "Dan": 4.0,
                "Eva": 5.0
            }
        ],
        [
            {
                "Alice": 0.3333333333333333,
                "Bob": 85.0,
                "Cindy": 22.0,
                "Dan": 33.0,
                "Eva": 17.0
            },
            {
                "Alice": 11.0,
                "Bob": 18.0,
                "Cindy": 19.0,
                "Dan": 13.0,
                "Eva": 15.0
            },
            {
                "Alice": 9.0,
                "Bob": 7.0,
                "Cindy": 7.0,
                "Dan": 8.0,
                "Eva": 10.0
            },
            {
                "Alice": 5.0,
                "Bob": 5.0,
                "Cindy": 5.0,
                "Dan": 4.0,
                "Eva": 4.0
            }
        ],
        [
            {
                "Alice": 28.0,
                "Bob": 28.0,
                "Cindy": 28.0,
                "Dan": 23.0,
                "Eva": 28.0
            },
            {
                "Alice": 26.0,
                "Bob": 14.0,
                "Cindy": 15.0,
                "Dan": 17.0,
                "Eva": 16.0
            },
            {
                "Alice": 12.0,
                "Bob": 10.0,
                "Cindy": 7.0,
                "Dan": 7.0,
                "Eva": 12.0
            },
            {
                "Alice": 2.0,
                "Bob": 5.0,
                "Cindy": 3.0,
                "Dan": 4.0,
                "Eva": 4.0
            }
        ]
    ],
    "negotiation": [
        [
            [],
            [],
            [],
            []
        ],
        [
            [],
            [],
            [],
            []
        ],
        [
            [],
            [],
            [],
            []
        ],
        [
            [],
            [],
            [],
            []
        ],
        [
            [],
            [],
            [],
            []
        ],
        [
            [],
            [],
            [],
            []
        ],
        [
            [],
            [],
            [],
            []
        ],
        [
            [],
            [],
            [],
            []
        ],
        [
            [],
            [],
            [],
            []
        ],
        [
            [],
            [],
            [],
            []
        ]
    ]
}